[
  {
    "key": "group_7d9936f661e61",
    "title": "Bloque: Header 5",
    "fields": [
      {
        "key": "field_7d3e5110160dc",
        "label": "Texto Botón",
        "name": "boton_texto",
        "aria-label": "",
        "type": "text",
        "instructions": "",
        "required": 0,
        "conditional_logic": 0,
        "wrapper": {
          "width": "",
          "class": "",
          "id": ""
        },
        "default_value": "Ver más",
        "maxlength": "",
        "placeholder": "",
        "prepend": "",
        "append": ""
      },
      {
        "key": "field_788b4cdae87c2",
        "label": "URL Botón",
        "name": "boton_url",
        "aria-label": "",
        "type": "url",
        "instructions": "",
        "required": 0,
        "conditional_logic": 0,
        "wrapper": {
          "width": "",
          "class": "",
          "id": ""
        },
        "default_value": "tel:",
        "maxlength": "",
        "placeholder": "",
        "prepend": "",
        "append": ""
      },
      {
        "key": "field_7cf77841ac408",
        "label": "Imagen",
        "name": "imagen",
        "aria-label": "",
        "type": "image",
        "instructions": "Fallback detectado en HTML original: <?= NAKAMA_OPTIONS[",
        "required": 0,
        "conditional_logic": 0,
        "wrapper": {
          "width": "",
          "class": "",
          "id": ""
        },
        "return_format": "url",
        "library": "all",
        "min_width": "",
        "min_height": "",
        "min_size": "",
        "max_width": "",
        "max_height": "",
        "max_size": "",
        "mime_types": "",
        "preview_size": "medium"
      },
      {
        "key": "field_auto_texto_ver_mas_4",
        "label": "Ver más",
        "name": "texto_ver_mas",
        "aria-label": "",
        "type": "text",
        "instructions": "",
        "required": 0,
        "conditional_logic": 0,
        "wrapper": {
          "width": "",
          "class": "",
          "id": ""
        },
        "default_value": "Ver más",
        "maxlength": "",
        "placeholder": "",
        "prepend": "",
        "append": ""
      },
      {
        "key": "field_auto_texto_ver_mas_2_5",
        "label": "Ver más",
        "name": "texto_ver_mas_2",
        "aria-label": "",
        "type": "text",
        "instructions": "",
        "required": 0,
        "conditional_logic": 0,
        "wrapper": {
          "width": "",
          "class": "",
          "id": ""
        },
        "default_value": "Ver más",
        "maxlength": "",
        "placeholder": "",
        "prepend": "",
        "append": ""
      }
    ],
    "location": [
      [
        {
          "param": "block",
          "operator": "==",
          "value": "acf/header-5"
        }
      ]
    ],
    "menu_order": 0,
    "position": "normal",
    "style": "default",
    "label_placement": "top",
    "instruction_placement": "label",
    "hide_on_screen": "",
    "active": true,
    "description": "",
    "show_in_rest": 0
  }
]